peakrdl_ipxact/__about__.py
peakrdl_ipxact/__init__.py
peakrdl_ipxact/__peakrdl__.py
peakrdl_ipxact/exporter.py
peakrdl_ipxact/importer.py
peakrdl_ipxact/typemaps.py
peakrdl_ipxact-3.5.0.dist-info/LICENSE
peakrdl_ipxact-3.5.0.dist-info/METADATA
peakrdl_ipxact-3.5.0.dist-info/WHEEL
peakrdl_ipxact-3.5.0.dist-info/entry_points.txt
peakrdl_ipxact-3.5.0.dist-info/top_level.txt
peakrdl_ipxact-3.5.0.dist-info/RECORD
