Metadata-Version: 2.1
Name: peakrdl-ipxact
Version: 3.5.0
Summary: Import and export IP-XACT XML to/from the systemrdl-compiler register model
Author: Alex Mykyta
License:                     GNU GENERAL PUBLIC LICENSE
Project-URL: Documentation, https://peakrdl-ipxact.readthedocs.io
Project-URL: Source, https://github.com/SystemRDL/PeakRDL-ipxact
Project-URL: Tracker, https://github.com/SystemRDL/PeakRDL-ipxact/issues
Project-URL: Changelog, https://github.com/SystemRDL/PeakRDL-ipxact/releases
Keywords: SystemRDL,PeakRDL,CSR,compiler,tool,registers,generator,IP-XACT
Classifier: Development Status :: 5 - Production/Stable
Classifier: Programming Language :: Python
Classifier: Programming Language :: Python :: 3
Classifier: Programming Language :: Python :: 3.6
Classifier: Programming Language :: Python :: 3.7
Classifier: Programming Language :: Python :: 3.8
Classifier: Programming Language :: Python :: 3.9
Classifier: Programming Language :: Python :: 3.10
Classifier: Programming Language :: Python :: 3.11
Classifier: Programming Language :: Python :: 3.12
Classifier: Programming Language :: Python :: 3 :: Only
Classifier: Intended Audience :: Developers
Classifier: License :: OSI Approved :: GNU General Public License v3 (GPLv3)
Classifier: Operating System :: OS Independent
Classifier: Topic :: Scientific/Engineering :: Electronic Design Automation (EDA)
Requires-Python: >=3.5.2
License-File: LICENSE
Requires-Dist: systemrdl-compiler<2,>=1.24.0
